django_test_migrations/__init__.py
django_test_migrations/checks/__init__.py
django_test_migrations/checks/autonames.py
django_test_migrations/checks/database_configuration.py
django_test_migrations/constants.py
django_test_migrations/contrib/__init__.py
django_test_migrations/contrib/django_checks.py
django_test_migrations/contrib/pytest_plugin.py
django_test_migrations/contrib/unittest_case.py
django_test_migrations/db/__init__.py
django_test_migrations/db/backends/__init__.py
django_test_migrations/db/backends/base/__init__.py
django_test_migrations/db/backends/base/configuration.py
django_test_migrations/db/backends/exceptions.py
django_test_migrations/db/backends/mysql/__init__.py
django_test_migrations/db/backends/mysql/configuration.py
django_test_migrations/db/backends/postgresql/__init__.py
django_test_migrations/db/backends/postgresql/configuration.py
django_test_migrations/db/backends/registry.py
django_test_migrations/db/checks/__init__.py
django_test_migrations/db/checks/statement_timeout.py
django_test_migrations/exceptions.py
django_test_migrations/logic/__init__.py
django_test_migrations/logic/datetime.py
django_test_migrations/logic/migrations.py
django_test_migrations/migrator.py
django_test_migrations/plan.py
django_test_migrations/py.typed
django_test_migrations/signals.py
django_test_migrations/sql.py
django_test_migrations/types.py
django_test_migrations-1.3.0.dist-info/LICENSE
django_test_migrations-1.3.0.dist-info/METADATA
django_test_migrations-1.3.0.dist-info/WHEEL
django_test_migrations-1.3.0.dist-info/entry_points.txt
django_test_migrations-1.3.0.dist-info/RECORD
