Metadata-Version: 2.1
Name: django-test-migrations
Version: 1.3.0
Summary: Test django schema and data migrations, including ordering
Home-page: https://github.com/wemake-services/django-test-migrations
License: MIT
Keywords: django,django-tests,django-migrations,django-orm,migrations,orm,sql,tests,test,pytest,pytest-plugin
Author: sobolevn
Author-email: mail@sobolevn.me
Requires-Python: >=3.8,<4.0
Classifier: Development Status :: 4 - Beta
Classifier: Framework :: Django
Classifier: Framework :: Django :: 3.2
Classifier: Framework :: Django :: 4.0
Classifier: Framework :: Django :: 4.1
Classifier: Intended Audience :: Developers
Classifier: License :: OSI Approved :: MIT License
Classifier: Operating System :: OS Independent
Classifier: Programming Language :: Python :: 3
Classifier: Programming Language :: Python :: 3.8
Classifier: Programming Language :: Python :: 3.9
Classifier: Programming Language :: Python :: 3.10
Classifier: Programming Language :: Python :: 3.11
Classifier: Topic :: Internet :: WWW/HTTP
Classifier: Topic :: Internet :: WWW/HTTP :: Dynamic Content
Classifier: Topic :: Software Development :: Libraries :: Python Modules
Requires-Dist: typing_extensions (>=3.6,<5)
Project-URL: Repository, https://github.com/wemake-services/django-test-migrations
